{
	"configurations" : 
	[
		{
			"directories" : 
			[
				{
					"build" : ".",
					"jsonFile" : "directory-.-Debug-f5ebdc15457944623624.json",
					"minimumCMakeVersion" : 
					{
						"string" : "3.27"
					},
					"projectIndex" : 0,
					"source" : ".",
					"targetIndexes" : 
					[
						0
					]
				}
			],
			"name" : "Debug",
			"projects" : 
			[
				{
					"directoryIndexes" : 
					[
						0
					],
					"name" : "Assignment1_Test",
					"targetIndexes" : 
					[
						0
					]
				}
			],
			"targets" : 
			[
				{
					"directoryIndex" : 0,
					"id" : "Assignment1_Test::@6890427a1f51a3e7e1df",
					"jsonFile" : "target-Assignment1_Test-Debug-713af4bea8b75012ff12.json",
					"name" : "Assignment1_Test",
					"projectIndex" : 0
				}
			]
		}
	],
	"kind" : "codemodel",
	"paths" : 
	{
		"build" : "/home/main/Desktop/BCIT_CST_2024/datacomm_2024/Assignment1-Test/cmake-build-debug",
		"source" : "/home/main/Desktop/BCIT_CST_2024/datacomm_2024/Assignment1-Test"
	},
	"version" : 
	{
		"major" : 2,
		"minor" : 6
	}
}
